{
  "level_1": {
    "Ramp1": {
      "id": 6,
      "x": 970,
      "y": 910,
      "width": 160,
      "height": 20,
      "speed": 1
    },

    "Ramp2": {
      "id": 6,
      "x": 70,
      "y": 710,
      "width": 160,
      "height": 20,
      "speed": 1
    },

    "Ramp3": {
      "id": 6,
      "x": 970,
      "y": 470,
      "width": 160,
      "height": 20,
      "speed": 1
    }
  },
  "level_2": {
    "Ramp1": {
      "id": 6,
      "x": 130,
      "y": 450,
      "width": 89,
      "height": 20,
      "speed": 1
    },

    "Ramp2": {
      "id": 6,
      "x": 411,
      "y": 650,
      "width": 89,
      "height": 20,
      "speed": 1
    },

    "Ramp3": {
      "id": 6,
      "x": 130,
      "y": 930,
      "width": 89,
      "height": 20,
      "speed": 1
    },
    "Ramp4": {
      "id": 6,
      "x": 981,
      "y": 450,
      "width": 89,
      "height": 20,
      "speed": 1
    },

    "Ramp5": {
      "id": 6,
      "x": 700,
      "y": 650,
      "width": 89,
      "height": 20,
      "speed": 1
    },

    "Ramp6": {
      "id": 6,
      "x": 981,
      "y": 930,
      "width": 89,
      "height": 20,
      "speed": 1
    }
  }

}